morejson/__init__.py
morejson/_version.py
morejson/core.py
morejson-1.1.5.dist-info/DESCRIPTION.rst
morejson-1.1.5.dist-info/METADATA
morejson-1.1.5.dist-info/RECORD
morejson-1.1.5.dist-info/WHEEL
morejson-1.1.5.dist-info/metadata.json
morejson-1.1.5.dist-info/top_level.txt
