Metadata-Version: 2.0
Name: morejson
Version: 1.1.5
Summary: Wraps Python json, supporting more Python built-in types.
Home-page: https://github.com/shaypal5/morejson
Author: Shay Palachy
Author-email: shay.palachy@gmail.com
License: MIT
Keywords: json datetime timedelta timezone frozenset
Platform: any
Classifier: Development Status :: 5 - Production/Stable
Classifier: License :: OSI Approved :: MIT License
Classifier: Programming Language :: Python
Classifier: Programming Language :: Python :: 2
Classifier: Programming Language :: Python :: 2.7
Classifier: Programming Language :: Python :: 3
Classifier: Programming Language :: Python :: 3.2
Classifier: Programming Language :: Python :: 3.3
Classifier: Programming Language :: Python :: 3.4
Classifier: Programming Language :: Python :: 3.5
Classifier: Programming Language :: Python :: 3.6
Classifier: Topic :: Software Development :: Libraries
Classifier: Topic :: Software Development :: Libraries :: Python Modules
Classifier: Topic :: Utilities
Classifier: Topic :: Other/Nonlisted Topic
Classifier: Intended Audience :: Developers
